AUTHORS
ChangeLog
LICENSE
README.md
setup.cfg
setup.py
db_dumper/__init__.py
db_dumper.egg-info/PKG-INFO
db_dumper.egg-info/SOURCES.txt
db_dumper.egg-info/dependency_links.txt
db_dumper.egg-info/not-zip-safe
db_dumper.egg-info/pbr.json
db_dumper.egg-info/top_level.txt
tests/__init__.py
tests/main_test.py