Metadata-Version: 1.0
Name: db-dumper
Version: 1.0.1
Summary: Load databases to and from YAML.
Home-page: https://github.com/chrisnorman7/
Author: Chris Norman
Author-email: chris.norman2@googlemail.com
License: MPL-2
Platform: UNKNOWN
